LICENSE
README.md
docs/Makefile
docs/make.bat
docs/source/acknowledgments.rst
docs/source/conf.py
docs/source/dependencies.rst
docs/source/index.rst
docs/source/installation.rst
docs/source/related_projects.rst
virtual_knitting_machine/Knitting_Machine.py
virtual_knitting_machine/Knitting_Machine_Snapshot.py
virtual_knitting_machine/Knitting_Machine_Specification.py
virtual_knitting_machine/__init__.py
virtual_knitting_machine/knitting_machine_exceptions/Knitting_Machine_Exception.py
virtual_knitting_machine/knitting_machine_exceptions/Needle_Exception.py
virtual_knitting_machine/knitting_machine_exceptions/Yarn_Carrier_Error_State.py
virtual_knitting_machine/knitting_machine_exceptions/__init__.py
virtual_knitting_machine/knitting_machine_exceptions/racking_errors.py
virtual_knitting_machine/knitting_machine_warnings/Carriage_Warning.py
virtual_knitting_machine/knitting_machine_warnings/Knitting_Machine_Warning.py
virtual_knitting_machine/knitting_machine_warnings/Needle_Warnings.py
virtual_knitting_machine/knitting_machine_warnings/Yarn_Carrier_System_Warning.py
virtual_knitting_machine/knitting_machine_warnings/__init__.py
virtual_knitting_machine/knitting_machine_warnings/carrier_operation_warnings.py
virtual_knitting_machine/machine_components/Needle_Bed.py
virtual_knitting_machine/machine_components/Needle_Bed_Snapshot.py
virtual_knitting_machine/machine_components/__init__.py
virtual_knitting_machine/machine_components/carriage_system/Carriage.py
virtual_knitting_machine/machine_components/carriage_system/Carriage_Pass_Direction.py
virtual_knitting_machine/machine_components/carriage_system/Carriage_Side.py
virtual_knitting_machine/machine_components/carriage_system/Carriage_Snapshot.py
virtual_knitting_machine/machine_components/carriage_system/__init__.py
virtual_knitting_machine/machine_components/needles/Needle.py
virtual_knitting_machine/machine_components/needles/Sheet_Identifier.py
virtual_knitting_machine/machine_components/needles/Sheet_Needle.py
virtual_knitting_machine-0.0.22.dist-info/LICENSE
virtual_knitting_machine-0.0.22.dist-info/METADATA
virtual_knitting_machine-0.0.22.dist-info/WHEEL
virtual_knitting_machine-0.0.22.dist-info/RECORD
