Metadata-Version: 2.1
Name: virtual-knitting-machine
Version: 0.0.22
Summary: A data structure representing the state and operations of a virtual V-Bed with sliders whole garment knitting machine based on the whole garment knitting machines made by Shima Seiki.
Home-page: https://mhofmann-khoury.github.io/virtual_knitting_machine/
License: MIT
Keywords: knit,machine knit,textile,Northeastern,ACT Lab,fabrication,Shima Seiki
Author: Megan Hofmann
Author-email: m.hofmann@northeastern.edu
Maintainer: Megan Hofmann
Maintainer-email: m.hofmann@northeastern.edu
Requires-Python: >=3.11,<3.14
Classifier: Development Status :: 2 - Pre-Alpha
Classifier: Intended Audience :: Developers
Classifier: Intended Audience :: Manufacturing
Classifier: Intended Audience :: Science/Research
Classifier: License :: OSI Approved :: MIT License
Classifier: Natural Language :: English
Classifier: Operating System :: OS Independent
Classifier: Programming Language :: Python :: 3
Classifier: Programming Language :: Python :: 3.11
Classifier: Programming Language :: Python :: 3.12
Classifier: Programming Language :: Python :: 3.13
Classifier: Topic :: Scientific/Engineering
Classifier: Typing :: Typed
Requires-Dist: knit-graphs (>=0.0.11)
Project-URL: Documentation, https://mhofmann-khoury.github.io/virtual_knitting_machine/
Project-URL: Repository, https://github.com/mhofmann-Khoury/virtual_knitting_machine
